pysnakegame/game/__init__.py
pysnakegame/game/colour.py
pysnakegame/game/snake.py
pysnakegame/game/core/__init__.py
pysnakegame/game/core/direction.py
pysnakegame/game/core/grid.py
pysnakegame/game/core/point.py
pysnakegame-0.0.7.dist-info/METADATA
pysnakegame-0.0.7.dist-info/WHEEL
pysnakegame-0.0.7.dist-info/top_level.txt
pysnakegame-0.0.7.dist-info/RECORD
